odoo/addons/account_banking_ach_base/README.rst
odoo/addons/account_banking_ach_base/__init__.py
odoo/addons/account_banking_ach_base/__manifest__.py
odoo/addons/account_banking_ach_base/i18n/account_banking_ach_base.pot
odoo/addons/account_banking_ach_base/models/__init__.py
odoo/addons/account_banking_ach_base/models/account_banking_mandate.py
odoo/addons/account_banking_ach_base/models/account_invoice.py
odoo/addons/account_banking_ach_base/models/account_payment_order.py
odoo/addons/account_banking_ach_base/models/base.py
odoo/addons/account_banking_ach_base/models/res_bank.py
odoo/addons/account_banking_ach_base/models/res_company.py
odoo/addons/account_banking_ach_base/models/res_partner.py
odoo/addons/account_banking_ach_base/readme/CONTRIBUTORS.rst
odoo/addons/account_banking_ach_base/readme/DESCRIPTION.rst
odoo/addons/account_banking_ach_base/readme/USAGE.rst
odoo/addons/account_banking_ach_base/static/description/icon.png
odoo/addons/account_banking_ach_base/static/description/index.html
odoo/addons/account_banking_ach_base/views/account_banking_mandate.xml
odoo/addons/account_banking_ach_base/views/account_invoice.xml
odoo/addons/account_banking_ach_base/views/res_bank.xml
odoo/addons/account_banking_ach_base/views/res_company.xml
odoo/addons/account_banking_ach_base/views/res_partner.xml
odoo12_addon_account_banking_ach_base-12.0.1.0.0.99.dev4.dist-info/METADATA
odoo12_addon_account_banking_ach_base-12.0.1.0.0.99.dev4.dist-info/WHEEL
odoo12_addon_account_banking_ach_base-12.0.1.0.0.99.dev4.dist-info/top_level.txt
odoo12_addon_account_banking_ach_base-12.0.1.0.0.99.dev4.dist-info/RECORD
